hwpkg.py
hwpkg-0.0.1.dist-info/LICENSE.txt
hwpkg-0.0.1.dist-info/METADATA
hwpkg-0.0.1.dist-info/WHEEL
hwpkg-0.0.1.dist-info/top_level.txt
hwpkg-0.0.1.dist-info/RECORD
