Metadata-Version: 2.1
Name: hwpkg
Version: 0.0.1
Summary: Honeywell demo package
Home-page: https://github.com/ashokdhudla/honeywell_pkg
Author: ashokdhudla@gmail.com
Author-email: UNKNOWN
License: UNKNOWN
Platform: UNKNOWN
Classifier: Programming Language :: Python :: 3
Classifier: License :: OSI Approved :: GNU General Public License v3 or later (GPLv3+)
Classifier: Operating System :: OS Independent
